CHANGES
MANIFEST.in
README.rst
development.ini
setup.cfg
setup.py
plorma/__init__.py
plorma.egg-info/PKG-INFO
plorma.egg-info/SOURCES.txt
plorma.egg-info/dependency_links.txt
plorma.egg-info/entry_points.txt
plorma.egg-info/not-zip-safe
plorma.egg-info/pbr.json
plorma.egg-info/requires.txt
plorma.egg-info/top_level.txt
plorma/alembic/alembic.ini
plorma/alembic/env.py
plorma/alembic/script.py.mako
plorma/alembic/versions/49d74299025_.py
plorma/fixtures/demo/01_users.json
plorma/fixtures/demo/02_profiles.json
plorma/fixtures/demo/10_tags.json
plorma/fixtures/demo/15_comments.json
plorma/fixtures/demo/20_tasks.json
plorma/fixtures/demo/30_sprints.json
plorma/fixtures/demo/990_users.json
plorma/fixtures/demo/999_usergroups.json
plorma/locale/plorma.pot
plorma/locale/de/LC_MESSAGES/plorma.mo
plorma/locale/de/LC_MESSAGES/plorma.po
plorma/model/README.txt
plorma/model/__init__.py
plorma/model/sprint.py
plorma/model/task.py
plorma/scaffolds/basic/development.ini_tmpl
plorma/scripts/__init__.py
plorma/static/README.txt
plorma/static/css/sprintboard.css
plorma/templates/README.txt
plorma/templates/custom-header.mako
plorma/templates/footer.mako
plorma/templates/index.mako
plorma/templates/sprint/board.mako
plorma/views/README.txt
plorma/views/__init__.py
plorma/views/board.py
plorma/views/home.py
plorma/views/sprints.py
plorma/views/tasks.py
plorma/views/forms/README.txt
plorma/views/forms/sprints.xml
plorma/views/forms/tasks.xml
plorma/views/tables/README.txt
plorma/views/tables/sprints.json
plorma/views/tables/tasks.json