Metadata-Version: 1.1
Name: plorma
Version: 0.3.1
Summary: Plorma is a task management application to plan organise and manage your tasks.
Home-page: UNKNOWN
Author: Torsten Irländer
Author-email: torsten@irlaender.de
License: UNKNOWN
Keywords: web wsgi bfg pylons pyramid
Platform: UNKNOWN
Classifier: Programming Language :: Python
Classifier: Framework :: Pyramid
Classifier: Topic :: Internet :: WWW/HTTP
Classifier: Topic :: Internet :: WWW/HTTP :: WSGI :: Application
